bytme/__init__.py
bytme/bytme.py
bytme-0.0.3.dist-info/LICENSE
bytme-0.0.3.dist-info/METADATA
bytme-0.0.3.dist-info/WHEEL
bytme-0.0.3.dist-info/top_level.txt
bytme-0.0.3.dist-info/RECORD
