Metadata-Version: 2.1
Name: bytme
Version: 0.0.3
Summary: for understanding pesky bytes
Home-page: https://github.com/pypa/sampleproject
Author: Nathan Murfey
Author-email: murfey.nathan@gmail.com
License: UNKNOWN
Platform: UNKNOWN
Classifier: Programming Language :: Python :: 3
Classifier: License :: OSI Approved :: MIT License
Classifier: Operating System :: OS Independent
Requires-Python: >=3.8
